<?xml version="1.0" encoding="utf-8" standalone="no"?>
<scenario xmlns="http://www.omnigroup.com/namespace/OmniPlan/v2" id="bL6MSkbXD1q">
  <prototype-task>
    <task id="t4294967294">
      <title>Task 1</title>
      <effort>28800</effort>
    </task>
  </prototype-task>
  <prototype-task>
    <task id="t4294967293">
      <title>Milestone 1</title>
      <type>milestone</type>
    </task>
  </prototype-task>
  <prototype-task>
    <task id="t4294967292">
      <title>Group 1</title>
      <type>group</type>
    </task>
  </prototype-task>
  <prototype-resource>
    <resource id="r4294967294">
      <name>Resource 1</name>
      <type>Staff</type>
    </resource>
  </prototype-resource>
  <prototype-resource>
    <resource id="r4294967293">
      <name>Equipment 1</name>
      <type>Equipment</type>
    </resource>
  </prototype-resource>
  <prototype-resource>
    <resource id="r4294967292">
      <name>Material 1</name>
      <type>Material</type>
      <units-available>0</units-available>
      <efficiency>0</efficiency>
    </resource>
  </prototype-resource>
  <prototype-resource>
    <resource id="r4294967291">
      <name>Group 1</name>
      <type>Group</type>
    </resource>
  </prototype-resource>
  <top-resource idref="r-1"/>
  <resource id="r-1">
    <type>Group</type>
    <child-resource idref="r1"/>
    <child-resource idref="r2"/>
    <child-resource idref="r4"/>
    <child-resource idref="r5"/>
  </resource>
  <resource id="r1">
    <name>Zeno Rocha</name>
    <type>Staff</type>
  </resource>
  <resource id="r2">
    <name>Designer da Bósnia</name>
    <type>Staff</type>
  </resource>
  <resource id="r4">
    <name>Eduardo Lundgren</name>
    <type>Staff</type>
  </resource>
  <resource id="r5">
    <name>English Revisor</name>
    <type>Staff</type>
  </resource>
  <top-task idref="t-1"/>
  <task id="t-1">
    <title>Pq</title>
    <type>group</type>
    <child-task idref="t6"/>
    <child-task idref="t3"/>
    <child-task idref="t109"/>
    <child-task idref="t10"/>
    <child-task idref="t25"/>
    <child-task idref="t13"/>
    <child-task idref="t115"/>
  </task>
  <task id="t2">
    <title>Study Component</title>
    <leveled-start>2001-01-01T10:00:00.000Z</leveled-start>
    <effort>28800</effort>
    <assignment idref="r1"/>
  </task>
  <task id="t3">
    <title>Documentation</title>
    <type>group</type>
    <child-task idref="t135"/>
    <child-task idref="t139"/>
    <child-task idref="t143"/>
    <child-task idref="t122"/>
  </task>
  <task id="t6">
    <title>Examples</title>
    <type>group</type>
    <child-task idref="t70"/>
    <child-task idref="t97"/>
    <child-task idref="t103"/>
  </task>
  <task id="t8">
    <title>Write text of this section</title>
    <leveled-start>2001-01-18T19:00:00.000Z</leveled-start>
    <effort>28800</effort>
    <assignment idref="r1"/>
  </task>
  <task id="t10">
    <title>Contribute</title>
    <type>group</type>
    <child-task idref="t8"/>
  </task>
  <task id="t13">
    <title>Website</title>
    <type>group</type>
    <child-task idref="t21"/>
    <child-task idref="t22"/>
    <child-task idref="t152"/>
  </task>
  <task id="t15">
    <title>Write text of this section</title>
    <leveled-start>2001-01-19T19:00:00.000Z</leveled-start>
    <effort>28800</effort>
    <assignment idref="r1"/>
  </task>
  <task id="t21">
    <title>Design</title>
    <leveled-start>2001-01-01T10:00:00.000Z</leveled-start>
    <effort>288000</effort>
    <assignment idref="r2"/>
  </task>
  <task id="t22">
    <title>Implement layout</title>
    <leveled-start>2001-01-30T19:00:00.000Z</leveled-start>
    <effort>144000</effort>
    <prerequisite-task idref="t21"/>
    <assignment idref="r1"/>
  </task>
  <task id="t25">
    <title>About</title>
    <type>group</type>
    <child-task idref="t15"/>
  </task>
  <task id="t70">
    <title>Component: Autocomplete</title>
    <type>group</type>
    <child-task idref="t2"/>
    <child-task idref="t92"/>
    <child-task idref="t94"/>
    <child-task idref="t95"/>
  </task>
  <task id="t92">
    <title>Code Basic Example</title>
    <leveled-start>2001-01-02T10:00:00.000Z</leveled-start>
    <effort>28800</effort>
    <prerequisite-task idref="t2"/>
    <assignment idref="r1"/>
  </task>
  <task id="t94">
    <title>Code Real World Example</title>
    <leveled-start>2001-01-03T10:00:00.000Z</leveled-start>
    <effort>28800</effort>
    <prerequisite-task idref="t92"/>
    <assignment idref="r1"/>
  </task>
  <task id="t95">
    <title>Technical Revision</title>
    <leveled-start>2001-01-04T10:00:00.000Z</leveled-start>
    <effort>28800</effort>
    <prerequisite-task idref="t94"/>
    <assignment idref="r4"/>
  </task>
  <task id="t96">
    <title>Study Component</title>
    <leveled-start>2001-01-03T19:00:00.000Z</leveled-start>
    <effort>28800</effort>
    <assignment idref="r1"/>
  </task>
  <task id="t97">
    <title>Component: Button</title>
    <type>group</type>
    <child-task idref="t96"/>
    <child-task idref="t98"/>
    <child-task idref="t99"/>
    <child-task idref="t100"/>
  </task>
  <task id="t98">
    <title>Code Basic Example</title>
    <leveled-start>2001-01-05T10:00:00.000Z</leveled-start>
    <effort>28800</effort>
    <prerequisite-task idref="t96"/>
    <assignment idref="r1"/>
  </task>
  <task id="t99">
    <title>Code Real World Example</title>
    <leveled-start>2001-01-08T10:00:00.000Z</leveled-start>
    <effort>28800</effort>
    <prerequisite-task idref="t98"/>
    <assignment idref="r1"/>
  </task>
  <task id="t100">
    <title>Technical Revision</title>
    <leveled-start>2001-01-09T10:00:00.000Z</leveled-start>
    <effort>28800</effort>
    <prerequisite-task idref="t99"/>
    <assignment idref="r4"/>
  </task>
  <task id="t102">
    <title>Study Component</title>
    <leveled-start>2001-01-08T19:00:00.000Z</leveled-start>
    <effort>28800</effort>
    <assignment idref="r1"/>
  </task>
  <task id="t103">
    <title>Component: Calendar</title>
    <type>group</type>
    <child-task idref="t102"/>
    <child-task idref="t104"/>
    <child-task idref="t105"/>
    <child-task idref="t106"/>
  </task>
  <task id="t104">
    <title>Code Basic Example</title>
    <leveled-start>2001-01-10T10:00:00.000Z</leveled-start>
    <effort>28800</effort>
    <prerequisite-task idref="t102"/>
    <assignment idref="r1"/>
  </task>
  <task id="t105">
    <title>Code Real World Example</title>
    <leveled-start>2001-01-11T10:00:00.000Z</leveled-start>
    <effort>28800</effort>
    <prerequisite-task idref="t104"/>
    <assignment idref="r1"/>
  </task>
  <task id="t106">
    <title>Technical Revision</title>
    <leveled-start>2001-01-12T10:00:00.000Z</leveled-start>
    <effort>28800</effort>
    <prerequisite-task idref="t105"/>
    <assignment idref="r4"/>
  </task>
  <task id="t109">
    <title>API Docs</title>
    <type>group</type>
    <child-task idref="t111"/>
    <child-task idref="t113"/>
    <child-task idref="t114"/>
  </task>
  <task id="t111">
    <title>Move from AlloyUI&apos;s repository to Alloyui.com repository</title>
    <leveled-start>2001-01-17T19:00:00.000Z</leveled-start>
    <effort>28800</effort>
    <assignment idref="r1"/>
  </task>
  <task id="t113">
    <title>Improve design according to the website&apos;s identity</title>
    <leveled-start>2001-01-19T10:00:00.000Z</leveled-start>
    <effort>144000</effort>
    <prerequisite-task idref="t111"/>
    <assignment idref="r2"/>
  </task>
  <task id="t114">
    <title>Implement layout</title>
    <leveled-start>2001-01-26T10:00:00.000Z</leveled-start>
    <effort>86400</effort>
    <prerequisite-task idref="t113"/>
    <assignment idref="r1"/>
  </task>
  <task id="t115">
    <title>Rosseta Stone</title>
    <type>group</type>
    <child-task idref="t118"/>
    <child-task idref="t120"/>
  </task>
  <task id="t118">
    <title>Move from AlloyUI&apos;s repository to another repository</title>
    <leveled-start>2001-01-23T19:00:00.000Z</leveled-start>
    <effort>28800</effort>
    <assignment idref="r1"/>
  </task>
  <task id="t120">
    <title>Update guide with the new versions of jQuery, YUI3 and AlloyUI</title>
    <leveled-start>2001-02-06T19:00:00.000Z</leveled-start>
    <effort>144000</effort>
    <prerequisite-task idref="t118"/>
    <assignment idref="r1"/>
  </task>
  <task id="t122">
    <title>Section: Getting Started</title>
    <type>group</type>
    <child-task idref="t124"/>
    <child-task idref="t132"/>
    <child-task idref="t134"/>
  </task>
  <task id="t124">
    <title>Write text about it</title>
    <leveled-start>2001-01-16T19:00:00.000Z</leveled-start>
    <effort>28800</effort>
    <assignment idref="r1"/>
  </task>
  <task id="t132">
    <title>Technical Revision</title>
    <leveled-start>2001-01-18T10:00:00.000Z</leveled-start>
    <effort>28800</effort>
    <prerequisite-task idref="t124"/>
    <assignment idref="r4"/>
  </task>
  <task id="t134">
    <title>English Revision</title>
    <leveled-start>2001-01-18T10:00:00.000Z</leveled-start>
    <effort>28800</effort>
    <prerequisite-task idref="t124"/>
    <assignment idref="r5"/>
  </task>
  <task id="t135">
    <title>Section: Autocomplete</title>
    <type>group</type>
    <child-task idref="t136"/>
    <child-task idref="t137"/>
    <child-task idref="t138"/>
  </task>
  <task id="t136">
    <title>Write text about it</title>
    <leveled-start>2001-01-11T19:00:00.000Z</leveled-start>
    <effort>28800</effort>
    <assignment idref="r1"/>
  </task>
  <task id="t137">
    <title>Technical Revision</title>
    <leveled-start>2001-01-15T10:00:00.000Z</leveled-start>
    <effort>28800</effort>
    <prerequisite-task idref="t136"/>
    <assignment idref="r4"/>
  </task>
  <task id="t138">
    <title>English Revision</title>
    <leveled-start>2001-01-15T10:00:00.000Z</leveled-start>
    <effort>28800</effort>
    <prerequisite-task idref="t136"/>
    <assignment idref="r5"/>
  </task>
  <task id="t139">
    <title>Section: Button</title>
    <type>group</type>
    <child-task idref="t140"/>
    <child-task idref="t141"/>
    <child-task idref="t142"/>
  </task>
  <task id="t140">
    <title>Write text about it</title>
    <leveled-start>2001-01-12T19:00:00.000Z</leveled-start>
    <effort>28800</effort>
    <assignment idref="r1"/>
  </task>
  <task id="t141">
    <title>Technical Revision</title>
    <leveled-start>2001-01-16T10:00:00.000Z</leveled-start>
    <effort>28800</effort>
    <prerequisite-task idref="t140"/>
    <assignment idref="r4"/>
  </task>
  <task id="t142">
    <title>English Revision</title>
    <leveled-start>2001-01-16T10:00:00.000Z</leveled-start>
    <effort>28800</effort>
    <prerequisite-task idref="t140"/>
    <assignment idref="r5"/>
  </task>
  <task id="t143">
    <title>Section: Calendar</title>
    <type>group</type>
    <child-task idref="t144"/>
    <child-task idref="t145"/>
    <child-task idref="t146"/>
  </task>
  <task id="t144">
    <title>Write text about it</title>
    <leveled-start>2001-01-15T19:00:00.000Z</leveled-start>
    <effort>28800</effort>
    <assignment idref="r1"/>
  </task>
  <task id="t145">
    <title>Technical Revision</title>
    <leveled-start>2001-01-17T10:00:00.000Z</leveled-start>
    <effort>28800</effort>
    <prerequisite-task idref="t144"/>
    <assignment idref="r4"/>
  </task>
  <task id="t146">
    <title>English Revision</title>
    <leveled-start>2001-01-17T10:00:00.000Z</leveled-start>
    <effort>28800</effort>
    <prerequisite-task idref="t144"/>
    <assignment idref="r5"/>
  </task>
  <task id="t152">
    <title>Define which websites are going to be displayed at Showcase&apos;s section
</title>
    <leveled-start>2001-01-22T19:00:00.000Z</leveled-start>
    <effort>28800</effort>
    <assignment idref="r1"/>
  </task>
  <critical-path root="-1" enabled="false" resources="false">
    <color r="1" g="0.5" b="0.5"/>
  </critical-path>
</scenario>
